LICENSE.txt
MANIFEST.in
README.rst
setup.cfg
setup.py
data/data_file
katzj/__init__.py
katzj/package_data.dat
katzj_test.egg-info/PKG-INFO
katzj_test.egg-info/SOURCES.txt
katzj_test.egg-info/dependency_links.txt
katzj_test.egg-info/entry_points.txt
katzj_test.egg-info/requires.txt
katzj_test.egg-info/top_level.txt