Metadata-Version: 1.1
Name: katzj-test
Version: 0.0.1
Summary: katzj Test Python project
Home-page: https://github.com/katzj/test-python-package
Author: Jeremy Katz
Author-email: jeremy@katzbox.net
License: MIT
Keywords: test package
Platform: UNKNOWN
Classifier: Development Status :: 3 - Alpha
Classifier: Intended Audience :: Developers
Classifier: Topic :: Software Development :: Build Tools
Classifier: License :: OSI Approved :: MIT License
Classifier: Programming Language :: Python :: 2
Classifier: Programming Language :: Python :: 2.7
Classifier: Programming Language :: Python :: 3
Classifier: Programming Language :: Python :: 3.3
Classifier: Programming Language :: Python :: 3.4
Classifier: Programming Language :: Python :: 3.5
